pythonfontinglibraryV1/__init__.py
syscolouringlibV1/__init__.py
syscolouringlibV1-1.0.0.dist-info/METADATA
syscolouringlibV1-1.0.0.dist-info/WHEEL
syscolouringlibV1-1.0.0.dist-info/top_level.txt
syscolouringlibV1-1.0.0.dist-info/RECORD
